sethealth/Client.py
sethealth/__init__.py
sethealth-1.8.0.dist-info/LICENSE
sethealth-1.8.0.dist-info/METADATA
sethealth-1.8.0.dist-info/WHEEL
sethealth-1.8.0.dist-info/top_level.txt
sethealth-1.8.0.dist-info/RECORD
