Metadata-Version: 2.1
Name: sethealth
Version: 1.8.0
Summary: Backend for sethealth authentication in python.
Home-page: https://github.com/sethealth/sethealth-py
Author: Sethealth team
Author-email: team@set.health
License: UNKNOWN
Keywords: API,authentication,sethealth
Platform: UNKNOWN
Classifier: Programming Language :: Python :: 3.3
Classifier: Programming Language :: Python :: 3.4
Classifier: Programming Language :: Python :: 3.5
Classifier: Programming Language :: Python :: 3.6
Classifier: Programming Language :: Python :: 3.7
Requires-Dist: requests
